server/__init__.py
server/main.py
huoshui_file_converter-0.1.1.dist-info/METADATA
huoshui_file_converter-0.1.1.dist-info/WHEEL
huoshui_file_converter-0.1.1.dist-info/entry_points.txt
huoshui_file_converter-0.1.1.dist-info/RECORD
