Metadata-Version: 2.4
Name: huoshui-file-converter
Version: 0.1.1
Summary: A secure MCP server for document format conversion using pypandoc
Project-URL: Homepage, https://github.com/huoshuiai/huoshui-file-converter
Project-URL: Repository, https://github.com/huoshuiai/huoshui-file-converter
Project-URL: Issues, https://github.com/huoshuiai/huoshui-file-converter/issues
Author-email: Huoshui AI <contact@huoshui.ai>
Maintainer-email: Huoshui AI <contact@huoshui.ai>
License: MIT
Keywords: conversion,document,docx,file-converter,format-conversion,html,markdown,mcp,pandoc
Classifier: Development Status :: 4 - Beta
Classifier: Environment :: Console
Classifier: Intended Audience :: Developers
Classifier: Intended Audience :: End Users/Desktop
Classifier: License :: OSI Approved :: MIT License
Classifier: Operating System :: OS Independent
Classifier: Programming Language :: Python :: 3
Classifier: Programming Language :: Python :: 3 :: Only
Classifier: Programming Language :: Python :: 3.12
Classifier: Topic :: Office/Business :: Office Suites
Classifier: Topic :: Software Development :: Libraries :: Python Modules
Classifier: Topic :: Text Processing :: Markup
Classifier: Topic :: Text Processing :: Markup :: HTML
Classifier: Topic :: Text Processing :: Markup :: Markdown
Classifier: Topic :: Utilities
Requires-Python: >=3.12
Requires-Dist: fastmcp>=2.9.2
Requires-Dist: pypandoc>=1.15
Provides-Extra: build
Requires-Dist: build>=0.8.0; extra == 'build'
Requires-Dist: requests>=2.25.0; extra == 'build'
Requires-Dist: toml>=0.10.2; extra == 'build'
Requires-Dist: twine>=4.0.0; extra == 'build'
Provides-Extra: dev
Requires-Dist: black>=22.0; extra == 'dev'
Requires-Dist: flake8>=4.0; extra == 'dev'
Requires-Dist: isort>=5.0; extra == 'dev'
Requires-Dist: mypy>=0.991; extra == 'dev'
Requires-Dist: pytest-cov>=4.0; extra == 'dev'
Requires-Dist: pytest>=7.0; extra == 'dev'
